CHANGES.txt
DEPENDENCES.txt
README.txt
setup.py
src/pd/__init__.py
src/pd.find.egg-info/PKG-INFO
src/pd.find.egg-info/SOURCES.txt
src/pd.find.egg-info/dependency_links.txt
src/pd.find.egg-info/namespace_packages.txt
src/pd.find.egg-info/not-zip-safe
src/pd.find.egg-info/requires.txt
src/pd.find.egg-info/top_level.txt
src/pd/find/__init__.py
src/pd/find/file.py
src/pd/find/filewrapper.py
src/pd/find/find.py
src/pd/find/findmixin.py
src/pd/find/pd.find.txt
src/pd/find/posixmixin.py
